spatial_maps/__init__.py
spatial_maps/bordercells.py
spatial_maps/fields.py
spatial_maps/gridcells.py
spatial_maps/maps.py
spatial_maps/stats.py
spatial_maps/tools.py
spatial_maps-0.2.0.dist-info/LICENSE
spatial_maps-0.2.0.dist-info/METADATA
spatial_maps-0.2.0.dist-info/WHEEL
spatial_maps-0.2.0.dist-info/top_level.txt
spatial_maps-0.2.0.dist-info/RECORD
